Metadata-Version: 1.1
Name: SpyCam
Version: 0.0.1
Summary: A raspberry Pi operated pan/tilt camera which uses Computer Vision
Home-page: https://www.youtube.com/watch?v=oHg5SJYRHA0
Author: Luca Barbas and Keagan Chasenski
Author-email: 3dkalucaphen@gmail.com
License: MIT
Keywords: Raspberry Pi
Platform: UNKNOWN
Classifier: Development Status :: 5 - Production/Stable
Classifier: Intended Audience :: Education
Classifier: Operating System :: POSIX :: Linux
Classifier: License :: OSI Approved :: MIT License
Classifier: Programming Language :: Python :: 3
